[
    {
        "Code": 70367,
        "Catégorie": "Traiteur sucré",
        "Produit": "Mini navette cuite noire décor sésame",
        "Prix Kg": null,
        "Prix Litre": null,
        "Portionnement": "Portion de 12 pièces",
        "Prix portion": 0.3176,
        "Colisage": "Colis de 108 unités",
        "Prix colis": 34.3,
        "Image": "CDP_0158.png"
    },
    {
        "Code": 22305,
        "Catégorie": "Traiteur sucré",
        "Produit": "Mini pain bretzel céréales cuit",
        "Prix Kg": null,
        "Prix Litre": null,
        "Portionnement": "Portion de 25g",
        "Prix portion": 0.2948,
        "Colisage": "Colis de 120 unités",
        "Prix colis": 35.38,
        "Image": "CDP_0158.png"
    },
    {
        "Code": 825765,
        "Catégorie": "Pains",
        "Produit": "Mini pain pita pour kebab Ø 60",
        "Prix Kg": null,
        "Prix Litre": null,
        "Portionnement": "Portion de 18g",
        "Prix portion": 0.334,
        "Colisage": "Colis de 220 unités",
        "Prix colis": 73.48,
        "Image": "CDP_0158.png"
    },
    {
        "Code": 70461,
        "Catégorie": "Pâtisserie à portionner",
        "Produit": "Mini pain naan cuit Ø 45",
        "Prix Kg": null,
        "Prix Litre": null,
        "Portionnement": "Portion de 10g",
        "Prix portion": 0.3112,
        "Colisage": "Colis de 200 unités",
        "Prix colis": 62.24,
        "Image": "CDP_0158.png"
    },
    {
        "Code": 822893,
        "Catégorie": "Pains",
        "Produit": "Mini bagel sésame Ø 50",
        "Prix Kg": null,
        "Prix Litre": null,
        "Portionnement": "Portion de 10g",
        "Prix portion": 0.2577,
        "Colisage": "Colis de 264 unités",
        "Prix colis": 68.02,
        "Image": "CDP_0158.png"
    }
]